rtl/alu.sv
module alu (
    input [31:0] a,
    input [31:0] b,
    input [2:0] op,
    output logic [31:0] result,
    output logic zero
);

always_comb begin

    case(op)
        3'b000:result = a + b; // Addition
        3'b001:result = a - b; // Subtraction
        3'b010:result = a & b; // Bitwise AND
        3'b011:result = a | b; // Bitwise OR
        3'b100:result = a ^ b; // Bitwise XOR
        default: result = 32'd0; // Default case
    endcase 

    zero = (result == 32'd0);// Set zero flag if resul
end

endmodule

wave.vcd
$version Generated by VerilatedVcd $end
$timescale 1ps $end
 $scope module TOP $end
  $var wire 32 # a [31:0] $end
  $var wire 32 $ b [31:0] $end
  $var wire 3 % op [2:0] $end
  $var wire 32 & result [31:0] $end
  $var wire 1 ' zero $end
  $scope module alu $end
   $var wire 32 # a [31:0] $end
   $var wire 32 $ b [31:0] $end
   $var wire 3 % op [2:0] $end
   $var wire 32 & result [31:0] $end
   $var wire 1 ' zero $end
  $upscope $end
 $upscope $end
$enddefinitions $end


#0
b11101101111110110101000111100010 #
b11100011111000010010110111100101 $
b000 %
b11010001110111000111111111000111 &
0'
#1
b00100001011101100000100010000001 #
b00101111000101010100110110100100 $
b010 %
b00100001000101000000100010000000 &
#2
b00110100010111100000111111111110 #
b11010011100100010101000101111110 $
b001 %
b01100000110011001011111010000000 &
#3
b10001000001101100100001000100010 #
b10011000011101011001111000011101 $
b000 %
b00100000101010111110000000111111 &
#4
b11110110111010100110110001110110 #
b01110110010000001100110101110001 $
b010 %
b01110110010000000100110001110000 &
#5
b11101100011110100001101010001110 #
b10111111101110000101100001101001 $
b10101100001110000001100000001000 &
#6
b10100111010100000101101011110111 #
b00100111101011000101010101110110 $
b000 %
b11001110111111001011000001101101 &
#7
b11100100011100001010001101110010 #
b11110110000110000011001011001001 $
b011 %
b11110110011110001011001111111011 &
#8
b00000010001001011011110001001101 #
b01001010100111111110011010001010 $
b001 %
b10110111100001011101010111000011 &
#9
b01100110000101000001011011010010 #
b01001100011101111101100010100110 $
b100 %
b00101010011000111100111001110100 &
#10
b10101000000010101001000000101011 #
b10100000100010010100000011100111 $
b011 %
b10101000100010111101000011101111 &
#11
b11101000011011011100010000011101 #
b11011111010001101110101110111000 $
b000 %
b11000111101101001010111111010101 &
#12
b11110110111100110010010100011111 #
b11010111000001001111001010111101 $
b010 %
b11010110000000000010000000011101 &
#13
b00001100111011001100011101011011 #
b10100100011110010100001101010111 $
b00000100011010000100001101010011 &
#14
b10110111101010110000101001000000 #
b11101110010010011110111111101111 $
b000 %
b10100101111101001111101000101111 &
#15
b01011101001100010000101011111100 #
b01010011010110011000010001111100 $
b10110000100010101000111101111000 &
#16
b01110000100011001000110010001111 #
b00100001000110101100001001110111 $
b001 %
b01001111011100011100101000011000 &
#17
b11010101001010101110111110001110 #
b11111110011101111011110101110011 $
b000 %
b11010011101000101010110100000001 &
#18
b10101101010001111001100001101011 #
b10111100101110010100100110000101 $
b100 %
b00010001111111101101000111101110 &
#19
b10011000110001011110010100110101 #
b00101011110000010000100101110011 $
b000 %
b11000100100001101110111010101000 &
#20
b00000110110111111001100000000101 #
b11001011100000110011000011100010 $
b010 %
b00000010100000110001000000000000 &
#21
b10110010110011111010100100000101 #
b11100111010110100101110000111011 $
b011 %
b11110111110111111111110100111111 &
#22
b00000110010100010010111000001100 #
b11100110010000110110010110001110 $
b001 %
b00100000000011011100100001111110 &
#23
b11010100111101110101101001010000 #
b10000110101110001010100010011011 $
b000 %
b01011011101100000000001011101011 &
#24
b10011000101010110111000101011000 #
b11111001100100111110111111100000 $
b010 %
b10011000100000110110000101000000 &
#25
b10100111111101110111010000000101 #
b11100101001001001001011001001010 $
b000 %
b10001101000111000000101001001111 &
#26
b10111010011011111010011100010110 #
b00011010010011010110111000001100 $
b010 %
b00011010010011010010011000000100 &
#27
b00111100110011101010101000111110 #
b10000000000011101001100100101001 $
b00000000000011101000100000101000 &
#28
b11001111011010001001001010110010 #
b10110011000000010010001001010010 $
b100 %
b01111100011010011011000011100000 &
#29
b01111100001001010101111100101110 #
b00111000000011010001110000111010 $
b001 %
b01000100000110000100001011110100 &
#30
b01000010001110110110100110010101 #
b10100011011111110101011100000111 $
b010 %
b00000010001110110100000100000101 &
#31
b11000010011000001101010000111111 #
b01110101100110010111101101111011 $
b01000000000000000101000000111011 &
#32
b10110101101000100110111011011010 #
b10110001100001100100101010101100 $
b011 %
b10110101101001100110111011111110 &
#33
b11101001110010110101100110001110 #
b10001000000011010001100110011010 $
b000 %
b01110001110110000111001100101000 &
#34
b00101010111100010010011110011110 #
b11010110010111100110110011100011 $
b100 %
b11111100101011110100101101111101 &
#35
b01100010000110011011110100000011 #
b11101101100111001001010111000000 $
b010 %
b01100000000110001001010100000000 &
#36
b10011100000001111100011011000010 #
b00000001100111001010111110110001 $
b001 %
b10011010011010110001011100010001 &
#37
b01110000000000111100001101111100 #
b01111101010110000010110011101100 $
b000 %
b11101101010110111111000001101000 &
#38
b01100000100110011010110111001000 #
b01100000001100011101011000101011 $
b001 %
b00000000011001111101011110011101 &
#39
b01111110010001011001100011010110 #
b11101001001111011010101100010101 $
b10010101000001111110110111000001 &
#40
b01100010010000111110100011100000 #
b00111111110110110001011100000101 $
b011 %
b01111111110110111111111111100101 &
#41
b01011000110111011101101011101000 #
b10010001100000100100011101110010 $
b000 %
b11101010011000000010001001011010 &
#42
b00110000000101001101011110111110 #
b11110000001110101111000011010100 $
b100 %
b11000000001011100010011101101010 &
#43
b00011001101110111101000001111001 #
b10110000000001100100011101000101 $
b10101001101111011001011100111100 &
#44
b11001100101100110000011010010010 #
b11111001111101111100100001110100 $
b001 %
b11010010101110110011111000011110 &
#45
b10110100101101001110110111001011 #
b11111001001001011001100110010010 $
b100 %
b01001101100100010111010001011001 &
#46
b10100010010100010110001100111100 #
b11101101100001110110101001110110 $
b000 %
b10001111110110001100110110110010 &
#47
b01101000111101111100100110001001 #
b01111110110100111000000001101100 $
b010 %
b01101000110100111000000000001000 &
#48
b01011010000000111000101001100110 #
b11000100111001000100100101000001 $
b011 %
b11011110111001111100101101100111 &
#49
b01010101101010111000000110011001 #
b10000001000000010111111110101011 $
b001 %
b11010100101010100000000111101110 &
#50
b00111001110000110110001011000000 #
b11100110000001111110100101001101 $
b010 %
b00100000000000110110000001000000 &
#51
b11001001100011101100010110001000 #
b11001010111101001111110010010010 $
b000 %
b10010100100000111100001000011010 &
#52
b01111110110000111001111010001111 #
b01110001101010010101011101011010 $
b001 %
b00001101000110100100011100110101 &
#53
b11000000001110100111010111101100 #
b11110010000000111110001101110010 $
b011 %
b11110010001110111111011111111110 &
#54
b10001000100000011110100001010110 #
b01011100010101101010100001000101 $
b11011100110101111110100001010111 &
#55
b01100000110110011100011001001111 #
b10111000100010100110101001100010 $
b11111000110110111110111001101111 &
#56
b01011110000100000111011110000111 #
b00001110001111100011011100000100 $
b100 %
b01010000001011100100000010000011 &
#57
b00010100000010001100110011110010 #
b00111010000000001101001010000011 $
b010 %
b00010000000000001100000010000010 &
#58
b01011010100000110100011100100000 #
b11001110000110110101110011110101 $
b100 %
b10010100100110000001101111010101 &
#59
b00010000101101111111110101010100 #
b01010000000111000101111011000001 $
b010 %
b00010000000101000101110001000000 &
#60
b11000100110010111101100010101100 #
b00100110111100100010110100000101 $
b000 %
b11101011101111100000010110110001 &
#61
b10101110001110110011010001111110 #
b11011010001101111000001000000010 $
b010 %
b10001010001100110000000000000010 &
#62
b11110011001011010000010111011000 #
b01000001111000100011100010110000 $
b011 %
b11110011111011110011110111111000 &
#63
b01110000000111101010010110100011 #
b11101001001001010100110000000101 $
b11111001001111111110110110100111 &
#64
b01010110000001111011011000011000 #
b01010000100001110110011001101101 $
b000 %
b10100110100011110001110010000101 &
#65
b01011001110010011001000001001110 #
b11100101111010011110110001010011 $
b100 %
b10111100001000000111110000011101 &
#66
b00001010111011110110001111111101 #
b00011001010011100100111110101010 $
b010 %
b00001000010011100100001110101000 &
#67
b11101110011101000010111100011000 #
b01001011011001000111000001011110 $
b001 %
b10100011000011111011111010111010 &
#68
b10100000100000110001000001111001 #
b01101101001101111111111010001011 $
b00110011010010110001000111101110 &
#69
b01000101010010110101100011100100 #
b00100100100110000000101101101100 $
b100 %
b01100001110100110101001110001000 &
#70
b10000100000011010011010011101000 #
b01110100000011010000101000011001 $
b11110000000000000011111011110001 &
#71
b00010101010011101111000011100001 #
b11011011010010111101010001011100 $
b011 %
b11011111010011111111010011111101 &
#72
b10100101101110010111111011000110 #
b01010100011010100111001001110110 $
b001 %
b01010001010011110000110001010000 &
#73
b00110001001011011100110011110010 #
b10110110000010111011000111100000 $
b01111011001000100001101100010010 &
#74
b01000000100111100110010000100101 #
b00001111110010101001110010010111 $
b010 %
b00000000100010100000010000000101 &
#75
b10001101111000100101001110001100 #
b01110001001110100010100011010010 $
b00000001001000100000000010000000 &
#76
b00000101010000001101101001011101 #
b01110110010011001101101111110110 $
b001 %
b10001110111100111111111001100111 &
#77
b11110010111001100111001000011001 #
b10100110111110000011111011000000 $
b011 %
b11110110111111100111111011011001 &
#78
b10000011011000010111110000011010 #
b11100010011010110100000100111000 $
b010 %
b10000010011000010100000000011000 &
#79
b01101110010110001010010110001100 #
b01111101010100101000010011011010 $
b001 %
b11110001000001100010000010110010 &
#80
b11101101001011100111010110111100 #
b11001100111011011100101101110110 $
b00100000010000001010101001000110 &
#81
b11110001000011101110101101001101 #
b00010010011110010001000111111001 $
b011 %
b11110011011111111111101111111101 &
#82
b10010001010010000011100101000101 #
b01100111110010011110101110110000 $
b100 %
b11110110100000011101001011110101 &
#83
b01001001011100010111011001001010 #
b11110001000010010010110110011111 $
b011 %
b11111001011110010111111111011111 &
#84
b01101010010101010100000010101010 #
b11000011110111100101001000111110 $
b11101011110111110101001010111110 &
#85
b10010100011101000100010101111111 #
b00011000111011101100001000110001 $
b001 %
b01111011100001011000001101001110 &
#86
b01111100011000000100100101111010 #
b10011111010101010010101010110011 $
b100 %
b11100011001101010110001111001001 &
#87
b10111101001110100110110000001111 #
b00000111100111100100111001110101 $
b000 %
b11000100110110001011101010000100 &
#88
b10110001101111000010101011101011 #
b10001000001101111111000100010001 $
b001 %
b00101001100001000011100111011010 &
#89
b10000100100011111111000010001110 #
b10111010110101001110101111101101 $
b000 %
b00111111011001001101110001111011 &
#90
b01101010000100101110100010011011 #
b00011111001001011100000000100111 $
b010 %
b00001010000000001100000000000011 &
#91
b10100100110010010100110111111110 #
b11101000101100101001100010010001 $
b10100000100000000000100010010000 &
#92
b11001010000101001011100101011001 #
b00010011100010100000100010101110 $
b001 %
b10110110100010101011000010101011 &
#93
b00100111000011101100011011001010 #
b01010000000100101011110110100010 $
b11010110111111000000100100101000 &
#94
b10011100011001101110100101010000 #
b11100001000111100111101101001100 $
b000 %
b01111101100001010110010010011100 &
#95
b00101001010101100101100110010110 #
b00100111111100100010010100001001 $
b010 %
b00100001010100100000000100000000 &
#96
b00101101011000111100100001100000 #
b00000000111010101001000111010000 $
b00000000011000101000000001000000 &
#97
b11001101011101110101000110111100 #
b01001010010000111010010011111000 $
b100 %
b10000111001101001111010101000100 &
#98
b10010101110011100101010011110011 #
b00111110101010000011011010101101 $
b010 %
b00010100100010000001010010100001 &
#99
b11000100101010010111011110011001 #
b01101001010000101111100001001101 $
b000 %
b00101101111011000110111111100110 &
