rtl/counter.v
module counter(
    input clk,
    input rst,
    output reg [7:0] count
);

always @(posedge clk) begin
    if (rst)
        count <= 8'd0;
    else
        count <= count + 1;
end

endmodule

wave.vcd
$version Generated by VerilatedVcd $end
$timescale 1ps $end
 $scope module TOP $end
  $var wire 1 # clk $end
  $var wire 1 $ rst $end
  $var wire 8 % count [7:0] $end
  $scope module counter $end
   $var wire 1 # clk $end
   $var wire 1 $ rst $end
   $var wire 8 % count [7:0] $end
  $upscope $end
 $upscope $end
$enddefinitions $end


#0
0#
1$
b00000000 %
#5
1#
#10
0#
#15
1#
#20
0#
#25
1#
#30
0#
0$
#35
1#
b00000001 %
#40
0#
#45
1#
b00000010 %
#50
0#
#55
1#
b00000011 %
#60
0#
#65
1#
b00000100 %
#70
0#
#75
1#
b00000101 %
#80
0#
#85
1#
b00000110 %
#90
0#
#95
1#
b00000111 %
