rtl/alu.sv
module alu (
    input [31:0] a,
    input [31:0] b,
    input [2:0] op,
    output logic [31:0] result,
    output logic zero
);

always_comb begin

    case(op)
        3'b000:result = a + b; // Addition
        3'b001:result = a - b; // Subtraction
        3'b010:result = a & b; // Bitwise AND
        3'b011:result = a | b; // Bitwise OR
        3'b100:result = a ^ b; // Bitwise XOR
        default: result = 32'd0; // Default case
    endcase 

    zero = (result == 32'd0);// Set zero flag if resul
end

endmodule

wave.vcd
$version Generated by VerilatedVcd $end
$timescale 1ps $end
 $scope module TOP $end
  $var wire 32 # a [31:0] $end
  $var wire 32 $ b [31:0] $end
  $var wire 3 % op [2:0] $end
  $var wire 32 & result [31:0] $end
  $var wire 1 ' zero $end
  $scope module alu $end
   $var wire 32 # a [31:0] $end
   $var wire 32 $ b [31:0] $end
   $var wire 3 % op [2:0] $end
   $var wire 32 & result [31:0] $end
   $var wire 1 ' zero $end
  $upscope $end
 $upscope $end
$enddefinitions $end


#0
b11101101111110110101000111100010 #
b11100011111000010010110111100101 $
b000 %
b11010001110111000111111111000111 &
0'
#1
b00100001011101100000100010000001 #
b00101111000101010100110110100100 $
b010 %
b00100001000101000000100010000000 &
#2
b00110100010111100000111111111110 #
b11010011100100010101000101111110 $
b001 %
b01100000110011001011111010000000 &
#3
b10001000001101100100001000100010 #
b10011000011101011001111000011101 $
b000 %
b00100000101010111110000000111111 &
#4
b11110110111010100110110001110110 #
b01110110010000001100110101110001 $
b010 %
b01110110010000000100110001110000 &
#5
b11101100011110100001101010001110 #
b10111111101110000101100001101001 $
b10101100001110000001100000001000 &
#6
b10100111010100000101101011110111 #
b00100111101011000101010101110110 $
b000 %
b11001110111111001011000001101101 &
#7
b11100100011100001010001101110010 #
b11110110000110000011001011001001 $
b011 %
b11110110011110001011001111111011 &
#8
b00000010001001011011110001001101 #
b01001010100111111110011010001010 $
b001 %
b10110111100001011101010111000011 &
#9
b01100110000101000001011011010010 #
b01001100011101111101100010100110 $
b100 %
b00101010011000111100111001110100 &
#10
b10101000000010101001000000101011 #
b10100000100010010100000011100111 $
b011 %
b10101000100010111101000011101111 &
#11
b11101000011011011100010000011101 #
b11011111010001101110101110111000 $
b000 %
b11000111101101001010111111010101 &
#12
b11110110111100110010010100011111 #
b11010111000001001111001010111101 $
b010 %
b11010110000000000010000000011101 &
#13
b00001100111011001100011101011011 #
b10100100011110010100001101010111 $
b00000100011010000100001101010011 &
#14
b10110111101010110000101001000000 #
b11101110010010011110111111101111 $
b000 %
b10100101111101001111101000101111 &
#15
b01011101001100010000101011111100 #
b01010011010110011000010001111100 $
b10110000100010101000111101111000 &
#16
b01110000100011001000110010001111 #
b00100001000110101100001001110111 $
b001 %
b01001111011100011100101000011000 &
#17
b11010101001010101110111110001110 #
b11111110011101111011110101110011 $
b000 %
b11010011101000101010110100000001 &
#18
b10101101010001111001100001101011 #
b10111100101110010100100110000101 $
b100 %
b00010001111111101101000111101110 &
#19
b10011000110001011110010100110101 #
b00101011110000010000100101110011 $
b000 %
b11000100100001101110111010101000 &
#20
b00000110110111111001100000000101 #
b11001011100000110011000011100010 $
b010 %
b00000010100000110001000000000000 &
#21
b10110010110011111010100100000101 #
b11100111010110100101110000111011 $
b011 %
b11110111110111111111110100111111 &
#22
b00000110010100010010111000001100 #
b11100110010000110110010110001110 $
b001 %
b00100000000011011100100001111110 &
#23
b11010100111101110101101001010000 #
b10000110101110001010100010011011 $
b000 %
b01011011101100000000001011101011 &
#24
b10011000101010110111000101011000 #
b11111001100100111110111111100000 $
b010 %
b10011000100000110110000101000000 &
#25
b10100111111101110111010000000101 #
b11100101001001001001011001001010 $
b000 %
b10001101000111000000101001001111 &
#26
b10111010011011111010011100010110 #
b00011010010011010110111000001100 $
b010 %
b00011010010011010010011000000100 &
#27
b00111100110011101010101000111110 #
b10000000000011101001100100101001 $
b00000000000011101000100000101000 &
#28
b11001111011010001001001010110010 #
b10110011000000010010001001010010 $
b100 %
b01111100011010011011000011100000 &
#29
b01111100001001010101111100101110 #
b00111000000011010001110000111010 $
b001 %
b01000100000110000100001011110100 &
#30
b01000010001110110110100110010101 #
b10100011011111110101011100000111 $
b010 %
b00000010001110110100000100000101 &
#31
b11000010011000001101010000111111 #
b01110101100110010111101101111011 $
b01000000000000000101000000111011 &
#32
b10110101101000100110111011011010 #
b10110001100001100100101010101100 $
b011 %
b10110101101001100110111011111110 &
#33
b11101001110010110101100110001110 #
b10001000000011010001100110011010 $
b000 %
b01110001110110000111001100101000 &
#34
b00101010111100010010011110011110 #
b11010110010111100110110011100011 $
b100 %
b11111100101011110100101101111101 &
#35
b01100010000110011011110100000011 #
b11101101100111001001010111000000 $
b010 %
b01100000000110001001010100000000 &
#36
b10011100000001111100011011000010 #
b00000001100111001010111110110001 $
b001 %
b10011010011010110001011100010001 &
#37
b01110000000000111100001101111100 #
b01111101010110000010110011101100 $
b000 %
b11101101010110111111000001101000 &
#38
b01100000100110011010110111001000 #
b01100000001100011101011000101011 $
b001 %
b00000000011001111101011110011101 &
#39
b01111110010001011001100011010110 #
b11101001001111011010101100010101 $
b10010101000001111110110111000001 &
#40
b01100010010000111110100011100000 #
b00111111110110110001011100000101 $
b011 %
b01111111110110111111111111100101 &
#41
b01011000110111011101101011101000 #
b10010001100000100100011101110010 $
b000 %
b11101010011000000010001001011010 &
#42
b00110000000101001101011110111110 #
b11110000001110101111000011010100 $
b100 %
b11000000001011100010011101101010 &
#43
b00011001101110111101000001111001 #
b10110000000001100100011101000101 $
b10101001101111011001011100111100 &
#44
b11001100101100110000011010010010 #
b11111001111101111100100001110100 $
b001 %
b11010010101110110011111000011110 &
#45
b10110100101101001110110111001011 #
b11111001001001011001100110010010 $
b100 %
b01001101100100010111010001011001 &
#46
b10100010010100010110001100111100 #
b11101101100001110110101001110110 $
b000 %
b10001111110110001100110110110010 &
#47
b01101000111101111100100110001001 #
b01111110110100111000000001101100 $
b010 %
b01101000110100111000000000001000 &
#48
b01011010000000111000101001100110 #
b11000100111001000100100101000001 $
b011 %
b11011110111001111100101101100111 &
#49
b01010101101010111000000110011001 #
b10000001000000010111111110101011 $
b001 %
b11010100101010100000000111101110 &
#50
b00111001110000110110001011000000 #
b11100110000001111110100101001101 $
b010 %
b00100000000000110110000001000000 &
#51
b11001001100011101100010110001000 #
b11001010111101001111110010010010 $
b000 %
b10010100100000111100001000011010 &
#52
b01111110110000111001111010001111 #
b01110001101010010101011101011010 $
b001 %
b00001101000110100100011100110101 &
#53
b11000000001110100111010111101100 #
b11110010000000111110001101110010 $
b011 %
b11110010001110111111011111111110 &
#54
b10001000100000011110100001010110 #
b01011100010101101010100001000101 $
b11011100110101111110100001010111 &
#55
b01100000110110011100011001001111 #
b10111000100010100110101001100010 $
b11111000110110111110111001101111 &
#56
b01011110000100000111011110000111 #
b00001110001111100011011100000100 $
b100 %
b01010000001011100100000010000011 &
#57
b00010100000010001100110011110010 #
b00111010000000001101001010000011 $
b010 %
b00010000000000001100000010000010 &
#58
b01011010100000110100011100100000 #
b11001110000110110101110011110101 $
b100 %
b10010100100110000001101111010101 &
#59
b00010000101101111111110101010100 #
b01010000000111000101111011000001 $
b010 %
b00010000000101000101110001000000 &
#60
b11000100110010111101100010101100 #
b00100110111100100010110100000101 $
b000 %
b11101011101111100000010110110001 &
#61
b10101110001110110011010001111110 #
b11011010001101111000001000000010 $
b010 %
b10001010001100110000000000000010 &
#62
b11110011001011010000010111011000 #
b01000001111000100011100010110000 $
b011 %
b11110011111011110011110111111000 &
#63
b01110000000111101010010110100011 #
b11101001001001010100110000000101 $
b11111001001111111110110110100111 &
#64
b01010110000001111011011000011000 #
b01010000100001110110011001101101 $
b000 %
b10100110100011110001110010000101 &
#65
b01011001110010011001000001001110 #
b11100101111010011110110001010011 $
b100 %
b10111100001000000111110000011101 &
#66
b00001010111011110110001111111101 #
b00011001010011100100111110101010 $
b010 %
b00001000010011100100001110101000 &
#67
b11101110011101000010111100011000 #
b01001011011001000111000001011110 $
b001 %
b10100011000011111011111010111010 &
#68
b10100000100000110001000001111001 #
b01101101001101111111111010001011 $
b00110011010010110001000111101110 &
#69
b01000101010010110101100011100100 #
b00100100100110000000101101101100 $
b100 %
b01100001110100110101001110001000 &
#70
b10000100000011010011010011101000 #
b01110100000011010000101000011001 $
b11110000000000000011111011110001 &
#71
b00010101010011101111000011100001 #
b11011011010010111101010001011100 $
b011 %
b11011111010011111111010011111101 &
#72
b10100101101110010111111011000110 #
b01010100011010100111001001110110 $
b001 %
b01010001010011110000110001010000 &
#73
b00110001001011011100110011110010 #
b10110110000010111011000111100000 $
b01111011001000100001101100010010 &
#74
b01000000100111100110010000100101 #
b00001111110010101001110010010111 $
b010 %
b00000000100010100000010000000101 &
#75
b10001101111000100101001110001100 #
b01110001001110100010100011010010 $
b00000001001000100000000010000000 &
#76
b00000101010000001101101001011101 #
b01110110010011001101101111110110 $
b001 %
b10001110111100111111111001100111 &
#77
b11110010111001100111001000011001 #
b10100110111110000011111011000000 $
b011 %
b11110110111111100111111011011001 &
#78
b10000011011000010111110000011010 #
b11100010011010110100000100111000 $
b010 %
b10000010011000010100000000011000 &
#79
b01101110010110001010010110001100 #
b01111101010100101000010011011010 $
b001 %
b11110001000001100010000010110010 &
#80
b11101101001011100111010110111100 #
b11001100111011011100101101110110 $
b00100000010000001010101001000110 &
#81
b11110001000011101110101101001101 #
b00010010011110010001000111111001 $
b011 %
b11110011011111111111101111111101 &
#82
b10010001010010000011100101000101 #
b01100111110010011110101110110000 $
b100 %
b11110110100000011101001011110101 &
#83
b01001001011100010111011001001010 #
b11110001000010010010110110011111 $
b011 %
b11111001011110010111111111011111 &
#84
b01101010010101010100000010101010 #
b11000011110111100101001000111110 $
b11101011110111110101001010111110 &
#85
b10010100011101000100010101111111 #
b00011000111011101100001000110001 $
b001 %
b01111011100001011000001101001110 &
#86
b01111100011000000100100101111010 #
b10011111010101010010101010110011 $
b100 %
b11100011001101010110001111001001 &
#87
b10111101001110100110110000001111 #
b00000111100111100100111001110101 $
b000 %
b11000100110110001011101010000100 &
#88
b10110001101111000010101011101011 #
b10001000001101111111000100010001 $
b001 %
b00101001100001000011100111011010 &
#89
b10000100100011111111000010001110 #
b10111010110101001110101111101101 $
b000 %
b00111111011001001101110001111011 &
#90
b01101010000100101110100010011011 #
b00011111001001011100000000100111 $
b010 %
b00001010000000001100000000000011 &
#91
b10100100110010010100110111111110 #
b11101000101100101001100010010001 $
b10100000100000000000100010010000 &
#92
b11001010000101001011100101011001 #
b00010011100010100000100010101110 $
b001 %
b10110110100010101011000010101011 &
#93
b00100111000011101100011011001010 #
b01010000000100101011110110100010 $
b11010110111111000000100100101000 &
#94
b10011100011001101110100101010000 #
b11100001000111100111101101001100 $
b000 %
b01111101100001010110010010011100 &
#95
b00101001010101100101100110010110 #
b00100111111100100010010100001001 $
b010 %
b00100001010100100000000100000000 &
#96
b00101101011000111100100001100000 #
b00000000111010101001000111010000 $
b00000000011000101000000001000000 &
#97
b11001101011101110101000110111100 #
b01001010010000111010010011111000 $
b100 %
b10000111001101001111010101000100 &
#98
b10010101110011100101010011110011 #
b00111110101010000011011010101101 $
b010 %
b00010100100010000001010010100001 &
#99
b11000100101010010111011110011001 #
b01101001010000101111100001001101 $
b000 %
b00101101111011000110111111100110 &
#100
b11100001111101000101010010100101 #
b11100010110111000111001010101011 $
b100 %
b00000011001010000010011000001110 &
#101
b11101001110000111010010111100010 #
b01000111011111100111010101101000 $
b000 %
b00110001010000100001101101001010 &
#102
b00010000011111110010011110110000 #
b01101011111001100101011111100100 $
b001 %
b10100100100110001100111111001100 &
#103
b00101010011101011111001011001000 #
b11101110100000101100001010100110 $
b010 %
b00101010000000001100001010000000 &
#104
b11011010101110101101100011100001 #
b11010111000000111001001011100001 $
b11010010000000101001000011100001 &
#105
b11101010010110101111011000111101 #
b00001101011000000111100110110001 $
b001 %
b11011100111110100111110010001100 &
#106
b10010100010110000100000110001101 #
b01101000110001010000111011101000 $
b00101011100100110011001010100101 &
#107
b00111000110111010110011011110010 #
b00000101100011101011100000101010 $
b100 %
b00111101010100111101111011011000 &
#108
b01011111101001011001011100100000 #
b11000110110110000011101010010101 $
b011 %
b11011111111111011011111110110101 &
#109
b10111100110000101010110011010001 #
b10011010100110011010101000010101 $
b10111110110110111010111011010101 &
#110
b10101011111101111011100101100010 #
b11111000111101101000001001010010 $
b001 %
b10110011000000010011011100010000 &
#111
b01101000111100110001101000001101 #
b11000111100011110000011110011000 $
b10100001011001000001001001110101 &
#112
b01100110100101000101011111110001 #
b10111101000010101000100011100100 $
b000 %
b00100011100111101110000011010101 &
#113
b01000100010001110001001110110101 #
b11100100101000111100101101111000 $
b010 %
b01000100000000110000001100110000 &
#114
b01000011001100101000011000110101 #
b11101110001101010110111001111110 $
b001 %
b01010100111111010001011110110111 &
#115
b11011111111010111001011111101111 #
b11011010011100100101010110010111 $
b100 %
b00000101100110011100001001111000 &
#116
b10111011010000100001011000101100 #
b11110111101000000100010001100010 $
b000 %
b10110010111000100101101010001110 &
#117
b01001101100100001001010111000011 #
b11100010000111110100001010010001 $
b011 %
b11101111100111111101011111010011 &
#118
b11011110001100101001000100101101 #
b00101010111100100010000000101101 $
b100 %
b11110100110000001011000100000000 &
#119
b11011011110000011100110110001000 #
b00000000000001110000011101100000 $
b000 %
b11011011110010001101010011101000 &
#120
b00000100001111000000100010111101 #
b00010000101010111000101100011101 $
b011 %
b00010100101111111000101110111101 &
#121
b10000100101000100001101100000110 #
b11111110110011010000101001110010 $
b11111110111011110001101101110110 &
#122
b00100110000110101010011110101011 #
b01110101001110100110000100100010 $
b000 %
b10011011010101010000100011001101 &
#123
b10010111100111010010011111010001 #
b11000010001100011100011011111001 $
b011 %
b11010111101111011110011111111001 &
#124
b00010001110011001011001000101111 #
b11010001111000000111111001101100 $
b001 %
b00111111111011000011001111000011 &
#125
b00010111101111011011110101101010 #
b01111000000110110011011101001011 $
b011 %
b01111111101111111011111101101011 &
#126
b00000010100110111011000111110100 #
b00111000100000001001110010000011 $
b000 %
b00111011000111000100111001110111 &
#127
b01111001010111100010110100110011 #
b11001011010100001100000111000010 $
b001 %
b10101110000011010110101101110001 &
#128
b00100110010010100010111011101101 #
b11111101110101010100100011011010 $
b010 %
b00100100010000000000100011001000 &
#129
b10011010101011011100101000011110 #
b11000011000101101001110001110001 $
b011 %
b11011011101111111101111001111111 &
#130
b00111001010000100111001011100101 #
b01011101110110111101101011011001 $
b01111101110110111111101011111101 &
#131
b00000001111111110100111001010000 #
b01110100111101010110011001010000 $
b010 %
b00000000111101010100011001010000 &
#132
b00111111111110110011010111100000 #
b00101011000001011000011111100000 $
b00101011000000010000010111100000 &
#133
b01111111000101111110000011100110 #
b11011000110100010100000110010001 $
b000 %
b01010111111010010010001001110111 &
#134
b01100000110010110010000110001110 #
b11010001011001011110000110100001 $
b010 %
b01000000010000010010000110000000 &
#135
b01011101111001000011010101110000 #
b11010101001001101000011111010101 $
b100 %
b10001000110000101011001010100101 &
#136
b01011111000000101000000010100001 #
b00110010011101100011111101100110 $
b001 %
b00101100100011000100000100111011 &
#137
b00000101010110010110101101110100 #
b10001101111111101111001101010011 $
b000 %
b10010011010110000101111011000111 &
#138
b01110011100001001101111110111001 #
b01111010100001101011011001101011 $
b11101110000010111001011000100100 &
#139
b00110110011000101010010110000101 #
b01100000111000100010001000111101 $
b011 %
b01110110111000101010011110111101 &
#140
b11010111001101011010100001011000 #
b00110000010110010001001100100010 $
b010 %
b00010000000100010000000000000000 &
#141
b11100011110010101001101010100111 #
b10010000000010010110011001010011 $
b10000000000010000000001000000011 &
#142
b10101001010001000101110000110011 #
b00010001100011100000000100100101 $
b00000001000001000000000000100001 &
#143
b00111110111000100010100000101010 #
b10011111101001101010101110111000 $
b100 %
b10100001010001001000001110010010 &
#144
b00111000110011010010101101000000 #
b00110100011101001010011100111011 $
b010 %
b00110000010001000010001100000000 &
#145
b01110111010001000000001101011011 #
b01100001101101011110101011001101 $
b000 %
b11011000111110011110111000101000 &
#146
b00110001111000001010110100111001 #
b10001000010010010010011111011100 $
b100 %
b10111001101010011000101011100101 &
#147
b10001101000011111100100100100000 #
b00111111110011010011011010000000 $
b000 %
b11001100110111001111111110100000 &
#148
b00100110111100101001010111100000 #
b01000110101001101001010000100010 $
b100 %
b01100000010101000000000111000010 &
#149
b00000100010100000000011001000000 #
b01000001011000101010100111001001 $
b001 %
b11000010111011010101110001110111 &
#150
b00100000101001101010111101010010 #
b00001100000010000001000000110001 $
b100 %
b00101100101011101011111101100011 &
#151
b00001111001001111011010011011011 #
b01101001101011011001010111001001 $
b011 %
b01101111101011111011010111011011 &
#152
b10101010111100101101010000001100 #
b01110001011011000111110100010010 $
b11111011111111101111110100011110 &
#153
b00101011001010000010110100010000 #
b01001110001011010011101100111111 $
b010 %
b00001010001010000010100100010000 &
#154
b00110011100000110110111010001001 #
b01110011000011000001011101000011 $
b001 %
b11000000011101110101011101000110 &
#155
b01111001000110111101101011001001 #
b00011110101101100110100100010110 $
b01011010011001010111000110110011 &
#156
b00001001100000100101110100001111 #
b10110011010111010010010011110111 $
b100 %
b10111010110111110111100111111000 &
#157
b10010111111110010110101001011111 #
b00111011000000011101001001001001 $
b000 %
b11010010111110110011110010101000 &
#158
b00111010011101010110001101111101 #
b10101001100001000111111101011011 $
b011 %
b10111011111101010111111101111111 &
#159
b11100000101110000111101001000111 #
b11100100011111101110001111010010 $
b001 %
b11111100001110011001011001110101 &
#160
b11000111100111000100000101011111 #
b11001100010011101010000110110110 $
b000 %
b10010011111010101110001100010101 &
#161
b00100011010100101000010000110010 #
b01001111011110010010001100100000 $
b01110010110010111010011101010010 &
#162
b01011100111100110000100011111100 #
b00111010000011110101111101111110 $
b10010111000000100110100001111010 &
#163
b10001000010011101100011001001000 #
b11101111011111000110001111111000 $
b01110111110010110010101001000000 &
#164
b10001111110011011100110010100110 #
b00111110011101010100011111001000 $
b011 %
b10111111111111011100111111101110 &
#165
b00110001111100100000100011111000 #
b01011001010100100110110100100101 $
b001 %
b11011000100111111001101111010011 &
#166
b11001100101110100001001011111010 #
b01100111110001101111111011111011 $
b011 %
b11101111111111101111111011111011 &
#167
b01101111011000010111011011001100 #
b10110110010011011000000111001101 $
b11111111011011011111011111001101 &
#168
b11101010110111011110011110011111 #
b10101101110001101111010111010111 $
b100 %
b01000111000110110001001001001000 &
#169
b01101110011100111011110100100110 #
b01010011101111011010111111111010 $
b00111101110011100001001011011100 &
#170
b01000001010011101011010000101010 #
b11111111010011100000111001101001 $
b10111110000000001011101001000011 &
#171
b00110010100000001001101110010001 #
b01101001111000100110100001010011 $
b011 %
b01111011111000101111101111010011 &
#172
b01101100110010001010110101111110 #
b01111001000111011110100111001011 $
b100 %
b00010101110101010100010010110101 &
#173
b00010110101110001011101101111011 #
b10011010011101111100111101001111 $
b010 %
b00010010001100001000101101001011 &
#174
b10111111010010000111101101010010 #
b10011001010000110000001000101001 $
b011 %
b10111111010010110111101101111011 &
#175
b00001100100110100011100110100101 #
b01100001101010100000010010101001 $
b001 %
b10101010111100000011010011111100 &
#176
b11001100000100101000111010011101 #
b00100000110100111101001010000100 $
b100 %
b11101100110000010101110000011001 &
#177
b00000110101001110111011001100000 #
b10111000101011011001110110111001 $
b001 %
b01001101111110011101100010100111 &
#178
b00110000011100000011111000110010 #
b01000011011000001010100101000001 $
b010 %
b00000000011000000010100000000000 &
#179
b10110110001000111000011001111100 #
b11010010110011101100111001001000 $
b000 %
b10001000111100100101010011000100 &
#180
b11010011100001101001101001011000 #
b11010010000101011011001011001111 $
b10100101100111000100110100100111 &
#181
b11001010011111110101100100110010 #
b00000101001001010110101001100111 $
b011 %
b11001111011111110111101101110111 &
#182
b10110100000110000000001011100110 #
b10000001000001100101100011001101 $
b100 %
b00110101000111100101101000101011 &
#183
b01101110010000100100010100111101 #
b01101011011001001001101000111101 $
b001 %
b00000010110111011010101100000000 &
#184
b11000100101000010111100101111010 #
b01111100100011001110110110101011 $
b01001000000101001000101111001111 &
#185
b01100110100000000100010110111011 #
b11100100011111110010100011111011 $
b100 %
b10000010111111110110110101000000 &
#186
b00100010100010111001001110000010 #
b01110001101101000110011000001100 $
b01010011001111111111010110001110 &
#187
b00111011111000100110011111101110 #
b10101110100111010111110101101000 $
b010 %
b00101010100000000110010101101000 &
#188
b10000111101100011000101111011000 #
b00111010101011101111100110101001 $
b001 %
b01001101000000101001001000101111 &
#189
b01000000010111110001100110001100 #
b11000000110101001101110111100110 $
b010 %
b01000000010101000001100110000100 &
#190
b00010111110111000001111111111111 #
b01110010010101001000110101111011 $
b011 %
b01110111110111001001111111111111 &
#191
b00010100101101010000111111110110 #
b01101001100100001001101000010011 $
b010 %
b00000000100100000000101000010010 &
#192
b00000000001111110011011101101111 #
b01110110011110001010001001101011 $
b001 %
b10001001110001101001010100000100 &
#193
b11000111010010101101100100111100 #
b10101110101111000101101001100110 $
b010 %
b10000110000010000101100000100100 &
#194
b01011101110001001001001101110110 #
b10011111110111100000111110101000 $
b00011101110001000000001100100000 &
#195
b11001100011001101110001100001101 #
b01111001101100010010001100000101 $
b01001000001000000010001100000101 &
#196
b10010100110000011010011100011110 #
b00001001100100011100001010101001 $
b001 %
b10001011001011111110010001110101 &
#197
b10111000000111011110011111101001 #
b11111111110110011001101101101111 $
b011 %
b11111111110111011111111111101111 &
#198
b10000001111000000011001000110001 #
b01010000110000100001011001101110 $
b010 %
b00000000110000000001001000100000 &
#199
b11010110001010011110000001011101 #
b00101111110101110000011000100110 $
b000 %
b00000110000000001110011010000011 &
#200
b01001011110011000110110010001110 #
b10100001001011011001111111011111 $
b11101100111110100000110001101101 &
#201
b00000101100100010011101001101100 #
b01001011011101101001011100010101 $
b011 %
b01001111111101111011111101111101 &
#202
b10110010011101101000111110010000 #
b01100101100111111001000001110000 $
b100 %
b11010111111010010001111111100000 &
#203
b10000101000000110100110101001101 #
b11101001100110110111011011101100 $
b01101100100110000011101110100001 &
#204
b01001100011011010001000100100010 #
b10101100100100101100101010011111 $
b001 %
b10011111110110100100011010000011 &
#205
b11011001101100001011000011101001 #
b11110010010111000110010001100111 $
b010 %
b11010000000100000010000001100001 &
#206
b00101011001111011101111011110000 #
b01010000110110011110111011011111 $
b011 %
b01111011111111011111111011111111 &
#207
b00101010110110000010000110110111 #
b10101110101000110010101111110001 $
b000 %
b11011001011110110100110110101000 &
#208
b11101011111000000101100000010111 #
b11010001011101111010010000000010 $
b011 %
b11111011111101111111110000010111 &
#209
b00101110110011000011001000101111 #
b00011001100100010101111000100100 $
b001 %
b00010101001110101101010000001011 &
#210
b01101001010111101100110010101011 #
b10000010100010110101101100100001 $
b011 %
b11101011110111111101111110101011 &
#211
b11000111001111100101111101010011 #
b00001010101000000010110000100100 $
b001 %
b10111100100111100011001100101111 &
#212
b00101111110110011001110101110100 #
b11110000101100000011111100000011 $
b000 %
b00100000100010011101110001110111 &
#213
b00111010010110111010010010111001 #
b00010110010100111111011100100001 $
b001 %
b00100100000001111010110110011000 &
#214
b01010000111110000100001010110011 #
b01101001010011111111101101010011 $
b000 %
b10111010010010000011111000000110 &
#215
b10110001101111010110000000001101 #
b00110011100000010111111100111110 $
b100 %
b10000010001111000001111100110011 &
#216
b10110001001000000011010101100011 #
b10000001111000000011010000011000 $
b010 %
b10000001001000000011010000000000 &
#217
b01000111111011001111101010110111 #
b10101110001011001101011011101111 $
b100 %
b11101001110000000010110001011000 &
#218
b01111100011001100110101000110100 #
b11101100011110111100010111011100 $
b011 %
b11111100011111111110111111111100 &
#219
b11000111001110000011111010100010 #
b01001000011000011010101101100000 $
b100 %
b10001111010110011001010111000010 &
#220
b11100111110010111010110101101010 #
b00111010001001001101110000101000 $
b001 %
b10101101101001101101000101000010 &
#221
b11001011000111001001000001001010 #
b11010111010101010111101001100101 $
b011 %
b11011111010111011111101001101111 &
#222
b00110010010010001101111000100010 #
b01001011010011000110010100011011 $
b001 %
b11100110111111000111100100000111 &
#223
b11010001001100011110110111101010 #
b11110010010101100101011000001101 $
b100 %
b00100011011001111011101111100111 &
#224
b10000001100011011110110010110000 #
b11011001100011110111010111001111 $
b000 %
b01011011000111010110001001111111 &
#225
b11110000100010000111110101000100 #
b00000110111011011000000101010101 $
b001 %
b11101001100110101111101111101111 &
#226
b10011111001011001000111101101101 #
b11101101000010010011100101011100 $
b010 %
b10001101000010000000100101001100 &
#227
b01100110101100101000001001000110 #
b01000110110111000101000001111000 $
b001 %
b00011111110101100011000111001110 &
#228
b00010000011001011110010011010001 #
b00111001100011100100100101001001 $
b010 %
b00010000000001000100000001000001 &
#229
b10110110101011101011101111100000 #
b00010001010101010111000001000111 $
b001 %
b10100101010110010100101110011001 &
#230
b00000000111110101010000000110001 #
b11101001110001010010110101000001 $
b000 %
b11101010101111111100110101110010 &
#231
b01111110110101010101100011010100 #
b01011001010101010001101100111100 $
b100 %
b00100111100000000100001111101000 &
#232
b00010111100010100101000101001001 #
b10101110001001100001011110010010 $
b010 %
b00000110000000100001000100000000 &
#233
b10100101111000011100001010110000 #
b00110111001110110110000100101011 $
b00100101001000010100000000100000 &
#234
b11111101110111011101101111000010 #
b10011110001000110101001111000000 $
b011 %
b11111111111111111101101111000010 &
#235
b10110101000001000011011011010000 #
b10101110000111110111111001011111 $
b010 %
b10100100000001000011011001010000 &
#236
b10000110101110000001000011000010 #
b01111011110011001000001100001000 $
b000 %
b00000010100001001001001111001010 &
#237
b11101001111111000111101010010100 #
b10101001010110111010111101001101 $
b001 %
b01000000101000001100101101000111 &
#238
b00100010100000010100011111111000 #
b11100111010001000100111000110100 $
b100 %
b11000101110001010000100111001100 &
#239
b01110010001010100000011110101010 #
b00100011010100101000000110111011 $
b011 %
b01110011011110101000011110111011 &
#240
b10100010000001110100001011110010 #
b00000100111111110111000110101001 $
b10100110111111110111001111111011 &
#241
b11011100111001010100000010001101 #
b00000101111110111110110010110100 $
b001 %
b11010110111010010101001111011001 &
#242
b10100000011111101011111010101111 #
b01111111111100011110110101001011 $
b010 %
b00100000011100001010110000001011 &
#243
b01100010010111110011111100010011 #
b10100100011000001110001001100001 $
b100 %
b11000110001111111101110101110010 &
#244
b11011101010101111100101110011000 #
b10111100010011111001001001011001 $
b010 %
b10011100010001111000001000011000 &
#245
b01000000011011011101111001010011 #
b01101001001101001001000110000001 $
b100 %
b00101001010110010100111111010010 &
#246
b10011100001111011101100001100110 #
b00010111100111010010011010011000 $
b10001011101000001111111011111110 &
#247
b01110111000110001111001111000000 #
b00100110111011101000100100100111 $
b010 %
b00100110000010001000000100000000 &
#248
b00101111000111100110110011110010 #
b01100011000010000111100100001111 $
b001 %
b11001100000101011111001111100011 &
#249
b00101000011010101001011011000001 #
b10110110011110111010011110110000 $
b100 %
b10011110000100010011000101110001 &
#250
b11101101100100000100110111110000 #
b10001001110001000100001000111111 $
b001 %
b01100011110011000000101110110001 &
#251
b11110011101011011001000111000011 #
b10001011100100001011110010110001 $
b000 %
b01111111001111100100111001110100 &
#252
b01010010100010000001010101010110 #
b01110101001100010001111100110101 $
b001 %
b11011101010101101111011000100001 &
#253
b01110110011100110010100100100011 #
b10110100000000011100010101111000 $
b100 %
b11000010011100101110110001011011 &
#254
b10111010111100011000111100100111 #
b11111100001000110010001010110010 $
b011 %
b11111110111100111010111110110111 &
#255
b11111111101011101010101110110101 #
b01011110110110000111100001000010 $
b11111111111111101111101111110111 &
#256
b10110111011110011000101110101000 #
b11001111101001001010001111101110 $
b010 %
b10000111001000001000001110101000 &
#257
b01010011010010000101110110000000 #
b00011100010110110100001101011110 $
b00010000010010000100000100000000 &
#258
b11000010000110110100010000100101 #
b00100011101010010010011001011110 $
b000 %
b11100101110001000110101010000011 &
#259
b00110011111000100001011110000010 #
b11010001000000011110011010100011 $
b010 %
b00010001000000000000011010000010 &
#260
b10001101110110011110110100101111 #
b10110100010111110001001111000100 $
b011 %
b10111101110111111111111111101111 &
#261
b00110010101110001000111000110011 #
b11101111101001110011110010100101 $
b000 %
b00100010010111111100101011011000 &
#262
b01101111001100010110101000000101 #
b11011010000001001000011101101011 $
b010 %
b01001010000000000000001000000001 &
#263
b10101000010010000100111011111101 #
b10101010100001111000011010101111 $
b10101000000000000000011010101101 &
#264
b10100001010100011100010111010011 #
b01010000101110100011001000110000 $
b00000000000100000000000000010000 &
#265
b11001110101101101001000010111111 #
b01011010100101011000010010110011 $
b01001010100101001000000010110011 &
#266
b10100010100101110111001000110010 #
b10101111011111101110111111001110 $
b10100010000101100110001000000010 &
#267
b11001011111111011010011001101011 #
b00010111010111010100000101100011 $
b100 %
b11011100101000001110011100001000 &
#268
b00010010001100100111000000101100 #
b01010001010011001000011101110100 $
b010 %
b00010000000000000000000000100100 &
#269
b11011001011011101001110000010101 #
b00110111001101000100001001110100 $
b00010001001001000000000000010100 &
#270
b10000101000010101111100000110000 #
b10010010010000010111000001111101 $
b000 %
b00010111010011000110100010101101 &
#271
b00011011001100101001000110000011 #
b01111001010001000110100111101110 $
b10010100011101101111101101110001 &
#272
b00110111010000110110010100111011 #
b10110101001010000101010001111001 $
b010 %
b00110101000000000100010000111001 &
#273
b00101110000001010010110111001100 #
b00110111011111000010100001110001 $
b000 %
b01100101100000010101011000111101 &
#274
b10100111110110110101001100010100 #
b11010011000110011001000111111000 $
b011 %
b11110111110110111101001111111100 &
#275
b11101001100000111101001001111001 #
b11101110001100101110101000010110 $
b000 %
b11010111101101101011110010001111 &
#276
b11001100111000001101001010000110 #
b00110111000010011110010111111101 $
b011 %
b11111111111010011111011111111111 &
#277
b01010110011100101000000111110001 #
b00110101000011101100101011010110 $
b100 %
b01100011011111000100101100100111 &
